{
  "case_id": "C3",
  "design": "pipelined_fft_256",
  "target_module": "cnorm",
  "mutant_id": "M005",
  "mutation_class": "predicate_inversion",
  "source_file": "/workspaces/digital-tools/examples/pipelined_fft_256_latest/cnorm.v",
  "source_line": 114,
  "original_snippet": "              if (ED)      begin",
  "mutated_snippet": "              if (!(ED))  begin",
  "failing_assertion_name": "A_rdy",
  "failing_assertion_text": "assert(RDY == $past(START))",
  "failing_assertion_file": "cnorm_prove_formal.sv",
  "failing_assertion_line": 57,
  "first_bad_cycle": 1,
  "key_signals": [
    "RDY",
    "ED",
    "START"
  ],
  "root_cause_class": "stuck_signal",
  "trace_path": "/workspaces/digital-tools/mgr/campaigns/pipelined_fft_256/runs/r2/M005/cnorm_prove/engine_0/trace_tb.v"
}